Quanlse/QHamiltonian.py
Quanlse/QOperator.py
Quanlse/QRegPool.py
Quanlse/QRpc.py
Quanlse/QTask.py
Quanlse/QWaveform.py
Quanlse/__init__.py
Quanlse/remoteOptimizer.py
Quanlse/remoteSimulator.py
Quanlse/remoteZNE.py
Quanlse/Define/Settings.py
Quanlse/Define/__init__.py
Quanlse/ErrorMitigation/__init__.py
Quanlse/ErrorMitigation/Utils/Utils.py
Quanlse/ErrorMitigation/Utils/Visualization.py
Quanlse/ErrorMitigation/Utils/__init__.py
Quanlse/ErrorMitigation/ZNE/Extrapolation.py
Quanlse/ErrorMitigation/ZNE/__init__.py
Quanlse/QOperation/FixedGate.py
Quanlse/QOperation/RotationGate.py
Quanlse/QOperation/__init__.py
Quanlse/QPlatform/Error.py
Quanlse/QPlatform/Utilities.py
Quanlse/QPlatform/__init__.py
Quanlse/Scheduler/GatePulsePair.py
Quanlse/Scheduler/SchedulerPipeline.py
Quanlse/Scheduler/SchedulerPulseGenerator.py
Quanlse/Scheduler/__init__.py
Quanlse/Superconduct/__init__.py
Quanlse/Superconduct/Calibration/Readout.py
Quanlse/Superconduct/Calibration/SingleQubit.py
Quanlse/Superconduct/Calibration/TwoQubit.py
Quanlse/Superconduct/Calibration/__init__.py
Quanlse/Superconduct/Lab/Experiment.py
Quanlse/Superconduct/Lab/ExperimentTask.py
Quanlse/Superconduct/Lab/Generator.py
Quanlse/Superconduct/Lab/LabSpace.py
Quanlse/Superconduct/Lab/Runner.py
Quanlse/Superconduct/Lab/Utils.py
Quanlse/Superconduct/Lab/__init__.py
Quanlse/Superconduct/SchedulerSupport/GeneratorCloud.py
Quanlse/Superconduct/SchedulerSupport/GeneratorPulseModel.py
Quanlse/Superconduct/SchedulerSupport/GeneratorRBPulse.py
Quanlse/Superconduct/SchedulerSupport/PipelineCenterAligned.py
Quanlse/Superconduct/SchedulerSupport/PipelineLeftAligned.py
Quanlse/Superconduct/SchedulerSupport/__init__.py
Quanlse/Superconduct/Simulator/PulseModel.py
Quanlse/Superconduct/Simulator/PulseSim1Q.py
Quanlse/Superconduct/Simulator/PulseSim2Q.py
Quanlse/Superconduct/Simulator/PulseSim3Q.py
Quanlse/Superconduct/Simulator/PulseSimQCQ.py
Quanlse/Superconduct/Simulator/ReadoutSim3Q.py
Quanlse/Superconduct/Simulator/Simulator2Q.py
Quanlse-2.2.0.dist-info/LICENSE
Quanlse-2.2.0.dist-info/METADATA
Quanlse-2.2.0.dist-info/WHEEL
Quanlse-2.2.0.dist-info/top_level.txt
Quanlse-2.2.0.dist-info/RECORD
